{
  "parent": "pvz:adventure/3-2",
  "display": {
    "icon": {
      "item": "pvz:challenge_envelope"
    },
    "title": {
      "translate": "advancement.pvz.3-3"
    },
    "description": {
      "translate": "advancement.pvz.3-3.desc"
    },
    "frame":"task",
    "show_toast": true,
    "announce_to_chat": true,
    "hidden": false
  },
  "criteria": {
    "in_world": {
      "trigger": "pvz:challenge",
      "conditions": {
        "type": "pvz:3-3"
      }
    }
  },
  "requirements": [[
    "in_world"
  ]],
  "rewards":{
    "experience":1500
  }
}