
{
  "parent": "pvz:adventure/3-9",
  "display": {
    "icon": {
      "item": "pvz:challenge_envelope"
    },
    "title": {
      "translate": "advancement.pvz.3-x"
    },
    "description": {
      "translate": "advancement.pvz.3-x.desc"
    },
    "frame":"challenge",
    "show_toast": true,
    "announce_to_chat": true,
    "hidden": false
  },
  "criteria": {
    "in_world": {
      "trigger": "pvz:challenge",
      "conditions": {
        "type": "pvz:3-x"
      }
    }
  },
  "requirements": [[
    "in_world"
  ]],
  "rewards":{
    "experience":8000
  }
}